odoo/addons/maintenance_equipment_usage/README.rst
odoo/addons/maintenance_equipment_usage/__init__.py
odoo/addons/maintenance_equipment_usage/__manifest__.py
odoo/addons/maintenance_equipment_usage/data/ir_sequence_data.xml
odoo/addons/maintenance_equipment_usage/i18n/es.po
odoo/addons/maintenance_equipment_usage/i18n/it.po
odoo/addons/maintenance_equipment_usage/i18n/maintenance_equipment_usage.pot
odoo/addons/maintenance_equipment_usage/models/__init__.py
odoo/addons/maintenance_equipment_usage/models/maintenance_equipment.py
odoo/addons/maintenance_equipment_usage/models/maintenance_equipment_usage.py
odoo/addons/maintenance_equipment_usage/readme/CONTRIBUTORS.md
odoo/addons/maintenance_equipment_usage/readme/DESCRIPTION.md
odoo/addons/maintenance_equipment_usage/security/ir.model.access.csv
odoo/addons/maintenance_equipment_usage/security/security.xml
odoo/addons/maintenance_equipment_usage/static/description/icon.png
odoo/addons/maintenance_equipment_usage/static/description/index.html
odoo/addons/maintenance_equipment_usage/tests/__init__.py
odoo/addons/maintenance_equipment_usage/tests/test_maintenance_equipment_usage.py
odoo/addons/maintenance_equipment_usage/views/maintenance_equipment_usage_views.xml
odoo/addons/maintenance_equipment_usage/views/maintenance_equipment_view.xml
odoo_addon_maintenance_equipment_usage-18.0.1.0.0.2.dist-info/METADATA
odoo_addon_maintenance_equipment_usage-18.0.1.0.0.2.dist-info/WHEEL
odoo_addon_maintenance_equipment_usage-18.0.1.0.0.2.dist-info/top_level.txt
odoo_addon_maintenance_equipment_usage-18.0.1.0.0.2.dist-info/RECORD
