Metadata-Version: 2.1
Name: odoo-addon-maintenance_equipment_usage
Version: 18.0.1.0.0.2
Requires-Python: >=3.10
Requires-Dist: odoo==18.0.*
Summary: Maintenance Equipment Usage
Home-page: https://github.com/OCA/maintenance
License: AGPL-3
Author: =?utf-8?q?C=C3=A9sar_Fern=C3=A1ndez=2C_Tecnativa=2C_Odoo_Community_Association_=28OCA=29?=
Author-email: support@odoo-community.org
Classifier: Programming Language :: Python
Classifier: Framework :: Odoo
Classifier: Framework :: Odoo :: 18.0
Classifier: License :: OSI Approved :: GNU Affero General Public License v3
